taskwarrior_mcp.py
taskwarrior_mcp-0.1.0.dist-info/METADATA
taskwarrior_mcp-0.1.0.dist-info/WHEEL
taskwarrior_mcp-0.1.0.dist-info/entry_points.txt
taskwarrior_mcp-0.1.0.dist-info/licenses/LICENSE
taskwarrior_mcp-0.1.0.dist-info/RECORD
