Metadata-Version: 2.4
Name: taskwarrior-mcp
Version: 0.1.0
Summary: MCP server for Taskwarrior CLI task management
Project-URL: Homepage, https://github.com/yourusername/taskwarrior-mcp
Project-URL: Repository, https://github.com/yourusername/taskwarrior-mcp
Project-URL: Issues, https://github.com/yourusername/taskwarrior-mcp/issues
License-Expression: MIT
License-File: LICENSE
Keywords: ai,llm,mcp,task-management,taskwarrior
Classifier: Development Status :: 4 - Beta
Classifier: Intended Audience :: Developers
Classifier: License :: OSI Approved :: MIT License
Classifier: Programming Language :: Python :: 3
Classifier: Programming Language :: Python :: 3.10
Classifier: Programming Language :: Python :: 3.11
Classifier: Programming Language :: Python :: 3.12
Requires-Python: >=3.10
Requires-Dist: mcp>=1.0.0
Requires-Dist: pydantic>=2.0.0
Provides-Extra: dev
Requires-Dist: black>=24.0.0; extra == 'dev'
Requires-Dist: mypy>=1.8.0; extra == 'dev'
Requires-Dist: pytest-asyncio>=0.23.0; extra == 'dev'
Requires-Dist: pytest-cov>=4.0.0; extra == 'dev'
Requires-Dist: pytest>=8.0.0; extra == 'dev'
Requires-Dist: ruff>=0.3.0; extra == 'dev'
